dt_tools/__init__.py
dt_tools/cli/demos/dt_ip_info_helper_demo.py
dt_tools/cli/demos/dt_net_demos.py
dt_tools/cli/demos/dt_net_helper_demo.py
dt_tools/net/ip_info_helper.py
dt_tools/net/net_helper.py
dt_tools/net/nic.py
dt_tools/net/wifi_scanner.py
dt_tools/net/wol.py
dt_net-0.1.36.dist-info/licenses/LICENSE
dt_net-0.1.36.dist-info/METADATA
dt_net-0.1.36.dist-info/WHEEL
dt_net-0.1.36.dist-info/RECORD
