Metadata-Version: 2.4
Name: dt-net
Version: 0.1.36
Summary: Network helper tools
License: MIT
License-File: LICENSE
Keywords: python,dt-tools,network
Author: Al DAmico
Author-email: JavaWiz1@hotmail.com
Requires-Python: >=3.10,<4.0
Classifier: License :: OSI Approved :: MIT License
Classifier: Programming Language :: Python
Classifier: Programming Language :: Python :: 3
Classifier: Programming Language :: Python :: 3.10
Classifier: Programming Language :: Python :: 3.11
Classifier: Programming Language :: Python :: 3.12
Classifier: Programming Language :: Python :: 3.13
Classifier: Programming Language :: Python :: 3.14
Requires-Dist: dt-console
Requires-Dist: dt-foundation
Requires-Dist: netifaces (>=0.11.0,<0.12.0)
Requires-Dist: python-dateutil (>=2.9,<3.0)
Requires-Dist: requests (>=2,<3)
Requires-Dist: scapy (>=2.5,<3.0)
Project-URL: Repository, https://github.com/JavaWiz1/dt-net
